opengeode_mymodule/__init__.py
opengeode_mymodule/libOpenGeode-MyModule_mylib.so
opengeode_mymodule/mylib.py
opengeode_mymodule/opengeode_mymodule_py_mylib.cpython-38-x86_64-linux-gnu.so
OpenGeode_MyModule-1.1.2.dist-info/METADATA
OpenGeode_MyModule-1.1.2.dist-info/WHEEL
OpenGeode_MyModule-1.1.2.dist-info/top_level.txt
OpenGeode_MyModule-1.1.2.dist-info/RECORD
