Metadata-Version: 2.1
Name: OpenGeode-MyModule
Version: 1.1.2
Summary: Template for creating your own OpenGeode modules
Home-page: https://github.com/Geode-solutions/OpenGeode-ModuleTemplate
Author: Geode-solutions
Author-email: contact@geode-solutions.com
License: MIT
Classifier: License :: OSI Approved :: MIT License
Requires-Dist: OpenGeode-core (==12.*,>=12.3.4)
